gym_gmtphasing/__init__.py
gym_gmtphasing/envs/__init__.py
gym_gmtphasing/envs/gmtphasing_env.py
gym_phasediversity/__init__.py
gym_phasediversity/envs/__init__.py
gym_phasediversity/envs/phasediversity_env.py
pripy/__init__.py
pripy/algos.py
pripy/core.py
pripy/util.py
pripy-0.1.8.dist-info/licenses/LICENSE
pripy-0.1.8.dist-info/METADATA
pripy-0.1.8.dist-info/WHEEL
pripy-0.1.8.dist-info/top_level.txt
pripy-0.1.8.dist-info/RECORD
