Metadata-Version: 2.4
Name: pripy
Version: 0.1.8
Summary: Phase Retrieval algorithms in Python
Home-page: https://github.com/jcranney/pripy.git
Author: Jesse Cranney
Author-email: jesse.cranney@anu.edu.au
Classifier: Programming Language :: Python :: 3
Classifier: License :: OSI Approved :: GNU General Public License (GPL)
Classifier: Operating System :: OS Independent
Requires-Python: >=3.7
License-File: LICENSE
Requires-Dist: numpy
Requires-Dist: scipy
Requires-Dist: aotools
Requires-Dist: torch
Requires-Dist: gym
Requires-Dist: gymnasium
Requires-Dist: pygame
Requires-Dist: ipython
Requires-Dist: matplotlib
Dynamic: license-file
